wasp/io_ndbc.py
wasp/io_sar.py
wasp/io_ww3.py
wasp/matching.py
wasp/partition.py
wasp/plotting.py
wasp/utils.py
wasp/wave_params.py
wasp_ocean-0.1.2.dist-info/licenses/LICENSE
wasp_ocean-0.1.2.dist-info/METADATA
wasp_ocean-0.1.2.dist-info/WHEEL
wasp_ocean-0.1.2.dist-info/top_level.txt
wasp_ocean-0.1.2.dist-info/RECORD
