Metadata-Version: 2.4
Name: wasp-ocean
Version: 0.1.2
Summary: Wave Spectra Partitioning - Watershed algorithm for ocean wave spectra
Author-email: "J.T. Carvalho" <jtcarvalho@gmail.com>
License: MIT
Project-URL: Homepage, https://github.com/jtcarvalho/wasp
Project-URL: Repository, https://github.com/jtcarvalho/wasp
Project-URL: Documentation, https://github.com/jtcarvalho/wasp/blob/main/README.md
Project-URL: Issues, https://github.com/jtcarvalho/wasp/issues
Keywords: waves,oceanography,SAR,WaveWatch3,spectral partitioning,watershed
Classifier: Development Status :: 3 - Alpha
Classifier: Intended Audience :: Science/Research
Classifier: Topic :: Scientific/Engineering :: Atmospheric Science
Classifier: Topic :: Scientific/Engineering :: Physics
Classifier: Programming Language :: Python :: 3
Classifier: Programming Language :: Python :: 3.10
Classifier: Programming Language :: Python :: 3.11
Classifier: Programming Language :: Python :: 3.12
Classifier: Programming Language :: Python :: 3.13
Requires-Python: >=3.10
License-File: LICENSE
Requires-Dist: numpy<3.0.0,>=2.1.0
Requires-Dist: pandas<3.0.0,>=2.2.0
Requires-Dist: scipy<2.0.0,>=1.14.0
Requires-Dist: xarray>=2024.11.0
Requires-Dist: netCDF4<2.0.0,>=1.5.4
Requires-Dist: matplotlib<4.0.0,>=3.8.0
Requires-Dist: scikit-image<1.0.0,>=0.22.0
Requires-Dist: tqdm<5.0.0,>=4.65.0
Dynamic: license-file
